odoo/addons/helpdesk_ticket_mail_message/CHANGELOG.md
odoo/addons/helpdesk_ticket_mail_message/README.rst
odoo/addons/helpdesk_ticket_mail_message/__init__.py
odoo/addons/helpdesk_ticket_mail_message/__manifest__.py
odoo/addons/helpdesk_ticket_mail_message/requirements.txt
odoo/addons/helpdesk_ticket_mail_message/data/helpdesk_data.xml
odoo/addons/helpdesk_ticket_mail_message/i18n/ca_ES.po
odoo/addons/helpdesk_ticket_mail_message/i18n/en_US.po
odoo/addons/helpdesk_ticket_mail_message/i18n/es.po
odoo/addons/helpdesk_ticket_mail_message/models/__init__.py
odoo/addons/helpdesk_ticket_mail_message/models/helpdesk_ticket.py
odoo/addons/helpdesk_ticket_mail_message/models/mail_message.py
odoo/addons/helpdesk_ticket_mail_message/models/mail_template.py
odoo/addons/helpdesk_ticket_mail_message/static/description/icon.png
odoo/addons/helpdesk_ticket_mail_message/static/src/css/font-awesome.min.css
odoo/addons/helpdesk_ticket_mail_message/static/src/css/list_renderer.css
odoo/addons/helpdesk_ticket_mail_message/static/src/fonts/FontAwesome.otf
odoo/addons/helpdesk_ticket_mail_message/static/src/fonts/fontawesome-webfont.eot
odoo/addons/helpdesk_ticket_mail_message/static/src/fonts/fontawesome-webfont.svg
odoo/addons/helpdesk_ticket_mail_message/static/src/fonts/fontawesome-webfont.ttf
odoo/addons/helpdesk_ticket_mail_message/static/src/fonts/fontawesome-webfont.woff
odoo/addons/helpdesk_ticket_mail_message/static/src/fonts/fontawesome-webfont.woff2
odoo/addons/helpdesk_ticket_mail_message/static/src/js/list_renderer.js
odoo/addons/helpdesk_ticket_mail_message/static/src/js/relative_date_formatter.js
odoo/addons/helpdesk_ticket_mail_message/tests/__init__.py
odoo/addons/helpdesk_ticket_mail_message/tests/test_mail_compose_message_wizard.py
odoo/addons/helpdesk_ticket_mail_message/tests/test_mail_message.py
odoo/addons/helpdesk_ticket_mail_message/views/helpdesk_ticket_view.xml
odoo/addons/helpdesk_ticket_mail_message/views/mail_template_view.xml
odoo12_addon_helpdesk_ticket_mail_message-12.0.1.1.0.dist-info/METADATA
odoo12_addon_helpdesk_ticket_mail_message-12.0.1.1.0.dist-info/WHEEL
odoo12_addon_helpdesk_ticket_mail_message-12.0.1.1.0.dist-info/top_level.txt
odoo12_addon_helpdesk_ticket_mail_message-12.0.1.1.0.dist-info/RECORD
