Metadata-Version: 2.1
Name: odoo12-addon-helpdesk-ticket-mail-message
Version: 12.0.1.1.0
Summary: Helpdesk Ticket Mail Message
Home-page: https://gitlab.com/somitcoop/erp-research/odoo-helpdesk
Author: Som It Cooperatiu SCCL, Som Connexió SCCL, Odoo Community Association (OCA)
Author-email: support@odoo-community.org
License: AGPL-3
Classifier: Programming Language :: Python
Classifier: Framework :: Odoo
Classifier: Framework :: Odoo :: 12.0
Classifier: License :: OSI Approved :: GNU Affero General Public License v3
Requires-Python: >=3.5
Requires-Dist: odoo12-addon-helpdesk-mgmt
Requires-Dist: odoo12-addon-mail-cc-and-to-text
Requires-Dist: odoo12-addon-web-widget-color
Requires-Dist: odoo12-addon-widget-list-limit-cell
Requires-Dist: odoo12-addon-widget-list-message
Requires-Dist: odoo12-addon-widget-list-row-color
Requires-Dist: odoo <12.1dev,>=12.0a
